xtlog/__init__.py
xtlog/config.py
xtlog/logger.py
xtlog/utils.py
xtlog-0.1.9.dist-info/METADATA
xtlog-0.1.9.dist-info/WHEEL
xtlog-0.1.9.dist-info/top_level.txt
xtlog-0.1.9.dist-info/RECORD
