Metadata-Version: 2.4
Name: xtlog
Version: 0.1.9
Summary: 基于 loguru 的高性能日志库
Author-email: sandorn <sandorn@live.cn>
License: MIT
Project-URL: Homepage, https://github.com/sandorn/xtlog
Project-URL: Repository, https://github.com/sandorn/xtlog
Project-URL: Documentation, https://github.com/sandorn/xtlog/blob/master/README.md
Classifier: Development Status :: 4 - Beta
Classifier: Intended Audience :: Developers
Classifier: License :: OSI Approved :: MIT License
Classifier: Programming Language :: Python :: 3
Classifier: Programming Language :: Python :: 3.8
Classifier: Programming Language :: Python :: 3.9
Classifier: Programming Language :: Python :: 3.10
Classifier: Programming Language :: Python :: 3.11
Classifier: Programming Language :: Python :: 3.12
Classifier: Topic :: Software Development :: Libraries :: Python Modules
Classifier: Topic :: System :: Logging
Requires-Python: >=3.8
Requires-Dist: loguru>=0.7.0
